{"config": {"exports": {"MSJET40.dll:msjet40_158": {"function": {"delta": "24", "convention": "stdcall"}, "ordinal": "158"}, "MSJET40.dll:msjet40_159": {"function": {"delta": "8", "convention": "stdcall"}, "ordinal": "159"}, "MSJET40.dll:msjet40_150": {"function": {"delta": "4", "convention": "stdcall"}, "ordinal": "150"}, "MSJET40.dll:msjet40_151": {"function": {"delta": "12", "convention": "stdcall"}, "ordinal": "151"}, "MSJET40.dll:msjet40_152": {"function": {"delta": "8", "convention": "stdcall"}, "ordinal": "152"}, "MSJET40.dll:msjet40_153": {"function": {"delta": "4", "convention": "stdcall"}, "ordinal": "153"}, "MSJET40.dll:msjet40_154": {"function": {"delta": "0", "convention": "stdcall"}, "ordinal": "154"}, "MSJET40.dll:msjet40_155": {"function": {"delta": "16", "convention": "stdcall"}, "ordinal": "155"}, "MSJET40.dll:msjet40_156": {"function": {"delta": "12", "convention": "stdcall"}, "ordinal": "156"}, "MSJET40.dll:msjet40_157": {"function": {"delta": "16", "convention": "stdcall"}, "ordinal": "157"}, "MSJET40.dll:msjet40_312": {"function": {"delta": "20", "convention": "stdcall"}, "ordinal": "312"}, "MSJET40.dll:msjet40_313": {"function": {"delta": "36", "convention": "stdcall"}, "ordinal": "313"}, "MSJET40.dll:msjet40_310": {"function": {"delta": "20", "convention": "stdcall"}, "ordinal": "310"}, "MSJET40.dll:msjet40_311": {"function": {"delta": "24", "convention": "stdcall"}, "ordinal": "311"}, "MSJET40.dll:msjet40_316": {"function": {"delta": "12", "convention": "stdcall"}, "ordinal": "316"}, "MSJET40.dll:msjet40_317": {"function": {"delta": "32", "convention": "stdcall"}, "ordinal": "317"}, "MSJET40.dll:msjet40_314": {"function": {"delta": "16", "convention": "stdcall"}, "ordinal": "314"}, "MSJET40.dll:msjet40_315": {"function": {"delta": "12", "convention": "stdcall"}, "ordinal": "315"}, "MSJET40.dll:msjet40_318": {"function": {"delta": "16", "convention": "stdcall"}, "ordinal": "318"}, "MSJET40.dll:msjet40_319": {"function": {"delta": "20", "convention": "stdcall"}, "ordinal": "319"}, "MSJET40.dll:DllUnregisterServer": {"function": {"delta": "-4", "convention": "stdcall"}, "ordinal": "59"}, "MSJET40.dll:msjet40_165": {"function": {"delta": "12", "convention": "stdcall"}, "ordinal": "165"}, "MSJET40.dll:msjet40_164": {"function": {"delta": "12", "convention": "stdcall"}, "ordinal": "164"}, "MSJET40.dll:msjet40_167": {"function": {"delta": "28", "convention": "stdcall"}, "ordinal": "167"}, "MSJET40.dll:msjet40_166": {"function": {"delta": "8", "convention": "stdcall"}, "ordinal": "166"}, "MSJET40.dll:msjet40_161": {"function": {"delta": "12", "convention": "stdcall"}, "ordinal": "161"}, "MSJET40.dll:msjet40_160": {"function": {"delta": "8", "convention": "stdcall"}, "ordinal": "160"}, "MSJET40.dll:msjet40_163": {"function": {"delta": "16", "convention": "stdcall"}, "ordinal": "163"}, "MSJET40.dll:msjet40_162": {"function": {"delta": "12", "convention": "stdcall"}, "ordinal": "162"}, "MSJET40.dll:msjet40_169": {"function": {"delta": "4", "convention": "stdcall"}, "ordinal": "169"}, "MSJET40.dll:msjet40_168": {"function": {"delta": "20", "convention": "stdcall"}, "ordinal": "168"}, "MSJET40.dll:msjet40_1006": {"function": {"delta": "16", "convention": "stdcall"}, "ordinal": "1006"}, "MSJET40.dll:msjet40_1007": {"function": {"delta": "12", "convention": "stdcall"}, "ordinal": "1007"}, "MSJET40.dll:msjet40_411": {"function": {"delta": "8", "convention": "stdcall"}, "ordinal": "411"}, "MSJET40.dll:msjet40_410": {"function": {"delta": "0", "convention": "stdcall"}, "ordinal": "410"}, "MSJET40.dll:msjet40_413": {"function": {"delta": "28", "convention": "stdcall"}, "ordinal": "413"}, "MSJET40.dll:msjet40_412": {"function": {"delta": "-4", "convention": "stdcall"}, "ordinal": "412"}, "MSJET40.dll:msjet40_804": {"function": {"delta": "16", "convention": "stdcall"}, "ordinal": "804"}, "MSJET40.dll:msjet40_802": {"function": {"delta": "0", "convention": "stdcall"}, "ordinal": "802"}, "MSJET40.dll:msjet40_803": {"function": {"delta": "28", "convention": "stdcall"}, "ordinal": "803"}, "MSJET40.dll:msjet40_801": {"function": {"delta": "24", "convention": "stdcall"}, "ordinal": "801"}, "MSJET40.dll:msjet40_172": {"function": {"delta": "24", "convention": "stdcall"}, "ordinal": "172"}, "MSJET40.dll:msjet40_173": {"function": {"delta": "8", "convention": "stdcall"}, "ordinal": "173"}, "MSJET40.dll:msjet40_170": {"function": {"delta": "8", "convention": "stdcall"}, "ordinal": "170"}, "MSJET40.dll:msjet40_171": {"function": {"delta": "24", "convention": "stdcall"}, "ordinal": "171"}, "MSJET40.dll:msjet40_176": {"function": {"delta": "16", "convention": "stdcall"}, "ordinal": "176"}, "MSJET40.dll:msjet40_177": {"function": {"delta": "20", "convention": "stdcall"}, "ordinal": "177"}, "MSJET40.dll:msjet40_174": {"function": {"delta": "8", "convention": "stdcall"}, "ordinal": "174"}, "MSJET40.dll:msjet40_175": {"function": {"delta": "16", "convention": "stdcall"}, "ordinal": "175"}, "MSJET40.dll:msjet40_178": {"function": {"delta": "0", "convention": "stdcall"}, "ordinal": "178"}, "MSJET40.dll:msjet40_179": {"function": {"delta": "16", "convention": "stdcall"}, "ordinal": "179"}, "MSJET40.dll:msjet40_409": {"function": {"delta": "12", "convention": "stdcall"}, "ordinal": "409"}, "MSJET40.dll:msjet40_403": {"function": {"delta": "4", "convention": "stdcall"}, "ordinal": "403"}, "MSJET40.dll:msjet40_401": {"function": {"delta": "8", "convention": "stdcall"}, "ordinal": "401"}, "MSJET40.dll:msjet40_404": {"function": {"delta": "4", "convention": "stdcall"}, "ordinal": "404"}, "MSJET40.dll:msjet40_52": {"function": {"delta": "4", "convention": "stdcall"}, "ordinal": "52"}, "MSJET40.dll:msjet40_53": {"function": {"delta": "16", "convention": "stdcall"}, "ordinal": "53"}, "MSJET40.dll:msjet40_50": {"function": {"delta": "16", "convention": "stdcall"}, "ordinal": "50"}, "MSJET40.dll:msjet40_51": {"function": {"delta": "12", "convention": "stdcall"}, "ordinal": "51"}, "MSJET40.dll:msjet40_56": {"function": {"delta": "20", "convention": "stdcall"}, "ordinal": "56"}, "MSJET40.dll:msjet40_57": {"function": {"delta": "16", "convention": "stdcall"}, "ordinal": "57"}, "MSJET40.dll:msjet40_54": {"function": {"delta": "12", "convention": "stdcall"}, "ordinal": "54"}, "MSJET40.dll:msjet40_55": {"function": {"delta": "4", "convention": "stdcall"}, "ordinal": "55"}, "MSJET40.dll:msjet40_107": {"function": {"delta": "8", "convention": "stdcall"}, "ordinal": "107"}, "MSJET40.dll:msjet40_106": {"function": {"delta": "12", "convention": "stdcall"}, "ordinal": "106"}, "MSJET40.dll:msjet40_105": {"function": {"delta": "16", "convention": "stdcall"}, "ordinal": "105"}, "MSJET40.dll:msjet40_104": {"function": {"delta": "0", "convention": "stdcall"}, "ordinal": "104"}, "MSJET40.dll:msjet40_103": {"function": {"delta": "12", "convention": "stdcall"}, "ordinal": "103"}, "MSJET40.dll:msjet40_102": {"function": {"delta": "8", "convention": "stdcall"}, "ordinal": "102"}, "MSJET40.dll:msjet40_101": {"function": {"delta": "24", "convention": "stdcall"}, "ordinal": "101"}, "MSJET40.dll:msjet40_109": {"function": {"delta": "4", "convention": "stdcall"}, "ordinal": "109"}, "MSJET40.dll:msjet40_108": {"function": {"delta": "4", "convention": "stdcall"}, "ordinal": "108"}, "MSJET40.dll:msjet40_188": {"function": {"delta": "0", "convention": "stdcall"}, "ordinal": "188"}, "MSJET40.dll:msjet40_187": {"function": {"delta": "4", "convention": "stdcall"}, "ordinal": "187"}, "MSJET40.dll:msjet40_186": {"function": {"delta": "12", "convention": "stdcall"}, "ordinal": "186"}, "MSJET40.dll:msjet40_185": {"function": {"delta": "20", "convention": "stdcall"}, "ordinal": "185"}, "MSJET40.dll:msjet40_184": {"function": {"delta": "16", "convention": "stdcall"}, "ordinal": "184"}, "MSJET40.dll:msjet40_181": {"function": {"delta": "12", "convention": "stdcall"}, "ordinal": "181"}, "MSJET40.dll:msjet40_180": {"function": {"delta": "16", "convention": "stdcall"}, "ordinal": "180"}, "MSJET40.dll:msjet40_1101": {"function": {"delta": "8", "convention": "stdcall"}, "ordinal": "1101"}, "MSJET40.dll:msjet40_909": {"function": {"delta": "28", "convention": "stdcall"}, "ordinal": "909"}, "MSJET40.dll:msjet40_908": {"function": {"delta": "36", "convention": "stdcall"}, "ordinal": "908"}, "MSJET40.dll:msjet40_907": {"function": {"delta": "36", "convention": "stdcall"}, "ordinal": "907"}, "MSJET40.dll:msjet40_906": {"function": {"delta": "44", "convention": "stdcall"}, "ordinal": "906"}, "MSJET40.dll:msjet40_114": {"function": {"delta": "24", "convention": "stdcall"}, "ordinal": "114"}, "MSJET40.dll:msjet40_115": {"function": {"delta": "20", "convention": "stdcall"}, "ordinal": "115"}, "MSJET40.dll:msjet40_116": {"function": {"delta": "16", "convention": "stdcall"}, "ordinal": "116"}, "MSJET40.dll:msjet40_117": {"function": {"delta": "24", "convention": "stdcall"}, "ordinal": "117"}, "MSJET40.dll:msjet40_110": {"function": {"delta": "24", "convention": "stdcall"}, "ordinal": "110"}, "MSJET40.dll:msjet40_111": {"function": {"delta": "4", "convention": "stdcall"}, "ordinal": "111"}, "MSJET40.dll:msjet40_112": {"function": {"delta": "16", "convention": "stdcall"}, "ordinal": "112"}, "MSJET40.dll:msjet40_113": {"function": {"delta": "8", "convention": "stdcall"}, "ordinal": "113"}, "MSJET40.dll:msjet40_118": {"function": {"delta": "20", "convention": "stdcall"}, "ordinal": "118"}, "MSJET40.dll:msjet40_119": {"function": {"delta": "12", "convention": "stdcall"}, "ordinal": "119"}, "MSJET40.dll:DllRegisterServer": {"function": {"delta": "-4", "convention": "stdcall"}, "ordinal": "58"}, "MSJET40.dll:msjet40_194": {"function": {"delta": "16", "convention": "stdcall"}, "ordinal": "194"}, "MSJET40.dll:msjet40_195": {"function": {"delta": "16", "convention": "stdcall"}, "ordinal": "195"}, "MSJET40.dll:msjet40_196": {"function": {"delta": "8", "convention": "stdcall"}, "ordinal": "196"}, "MSJET40.dll:msjet40_190": {"function": {"delta": "0", "convention": "stdcall"}, "ordinal": "190"}, "MSJET40.dll:msjet40_191": {"function": {"delta": "12", "convention": "stdcall"}, "ordinal": "191"}, "MSJET40.dll:msjet40_192": {"function": {"delta": "8", "convention": "stdcall"}, "ordinal": "192"}, "MSJET40.dll:msjet40_193": {"function": {"delta": "20", "convention": "stdcall"}, "ordinal": "193"}, "MSJET40.dll:msjet40_910": {"function": {"delta": "40", "convention": "stdcall"}, "ordinal": "910"}, "MSJET40.dll:msjet40_911": {"function": {"delta": "8", "convention": "stdcall"}, "ordinal": "911"}, "MSJET40.dll:msjet40_912": {"function": {"delta": "20", "convention": "stdcall"}, "ordinal": "912"}, "MSJET40.dll:msjet40_913": {"function": {"delta": "12", "convention": "stdcall"}, "ordinal": "913"}, "MSJET40.dll:msjet40_121": {"function": {"delta": "8", "convention": "stdcall"}, "ordinal": "121"}, "MSJET40.dll:msjet40_120": {"function": {"delta": "4", "convention": "stdcall"}, "ordinal": "120"}, "MSJET40.dll:msjet40_123": {"function": {"delta": "8", "convention": "stdcall"}, "ordinal": "123"}, "MSJET40.dll:msjet40_122": {"function": {"delta": "4", "convention": "stdcall"}, "ordinal": "122"}, "MSJET40.dll:msjet40_125": {"function": {"delta": "8", "convention": "stdcall"}, "ordinal": "125"}, "MSJET40.dll:msjet40_124": {"function": {"delta": "12", "convention": "stdcall"}, "ordinal": "124"}, "MSJET40.dll:msjet40_127": {"function": {"delta": "4", "convention": "stdcall"}, "ordinal": "127"}, "MSJET40.dll:msjet40_126": {"function": {"delta": "8", "convention": "stdcall"}, "ordinal": "126"}, "MSJET40.dll:msjet40_129": {"function": {"delta": "4", "convention": "stdcall"}, "ordinal": "129"}, "MSJET40.dll:msjet40_128": {"function": {"delta": "12", "convention": "stdcall"}, "ordinal": "128"}, "MSJET40.dll:msjet40_321": {"function": {"delta": "16", "convention": "stdcall"}, "ordinal": "321"}, "MSJET40.dll:msjet40_320": {"function": {"delta": "0", "convention": "stdcall"}, "ordinal": "320"}, "MSJET40.dll:msjet40_326": {"function": {"delta": "24", "convention": "stdcall"}, "ordinal": "326"}, "MSJET40.dll:msjet40_325": {"function": {"delta": "20", "convention": "stdcall"}, "ordinal": "325"}, "MSJET40.dll:msjet40_138": {"function": {"delta": "36", "convention": "stdcall"}, "ordinal": "138"}, "MSJET40.dll:msjet40_139": {"function": {"delta": "20", "convention": "stdcall"}, "ordinal": "139"}, "MSJET40.dll:msjet40_136": {"function": {"delta": "16", "convention": "stdcall"}, "ordinal": "136"}, "MSJET40.dll:msjet40_137": {"function": {"delta": "24", "convention": "stdcall"}, "ordinal": "137"}, "MSJET40.dll:msjet40_134": {"function": {"delta": "12", "convention": "stdcall"}, "ordinal": "134"}, "MSJET40.dll:msjet40_135": {"function": {"delta": "16", "convention": "stdcall"}, "ordinal": "135"}, "MSJET40.dll:msjet40_132": {"function": {"delta": "16", "convention": "stdcall"}, "ordinal": "132"}, "MSJET40.dll:msjet40_133": {"function": {"delta": "24", "convention": "stdcall"}, "ordinal": "133"}, "MSJET40.dll:msjet40_130": {"function": {"delta": "4", "convention": "stdcall"}, "ordinal": "130"}, "MSJET40.dll:msjet40_131": {"function": {"delta": "28", "convention": "stdcall"}, "ordinal": "131"}, "MSJET40.dll:msjet40_149": {"function": {"delta": "20", "convention": "stdcall"}, "ordinal": "149"}, "MSJET40.dll:msjet40_148": {"function": {"delta": "16", "convention": "stdcall"}, "ordinal": "148"}, "MSJET40.dll:msjet40_143": {"function": {"delta": "24", "convention": "stdcall"}, "ordinal": "143"}, "MSJET40.dll:msjet40_142": {"function": {"delta": "12", "convention": "stdcall"}, "ordinal": "142"}, "MSJET40.dll:msjet40_141": {"function": {"delta": "20", "convention": "stdcall"}, "ordinal": "141"}, "MSJET40.dll:msjet40_140": {"function": {"delta": "28", "convention": "stdcall"}, "ordinal": "140"}, "MSJET40.dll:msjet40_147": {"function": {"delta": "20", "convention": "stdcall"}, "ordinal": "147"}, "MSJET40.dll:msjet40_146": {"function": {"delta": "20", "convention": "stdcall"}, "ordinal": "146"}, "MSJET40.dll:msjet40_145": {"function": {"delta": "20", "convention": "stdcall"}, "ordinal": "145"}, "MSJET40.dll:msjet40_144": {"function": {"delta": "20", "convention": "stdcall"}, "ordinal": "144"}, "MSJET40.dll:msjet40_305": {"function": {"delta": "36", "convention": "stdcall"}, "ordinal": "305"}, "MSJET40.dll:msjet40_304": {"function": {"delta": "24", "convention": "stdcall"}, "ordinal": "304"}, "MSJET40.dll:msjet40_307": {"function": {"delta": "4", "convention": "stdcall"}, "ordinal": "307"}, "MSJET40.dll:msjet40_306": {"function": {"delta": "16", "convention": "stdcall"}, "ordinal": "306"}, "MSJET40.dll:msjet40_301": {"function": {"delta": "20", "convention": "stdcall"}, "ordinal": "301"}, "MSJET40.dll:msjet40_303": {"function": {"delta": "8", "convention": "stdcall"}, "ordinal": "303"}, "MSJET40.dll:msjet40_302": {"function": {"delta": "12", "convention": "stdcall"}, "ordinal": "302"}, "MSJET40.dll:msjet40_309": {"function": {"delta": "24", "convention": "stdcall"}, "ordinal": "309"}, "MSJET40.dll:msjet40_308": {"function": {"delta": "20", "convention": "stdcall"}, "ordinal": "308"}, "MSJET40.dll:msjet40_1008": {"function": {"delta": "24", "convention": "stdcall"}, "ordinal": "1008"}, "MSJET40.dll:msjet40_1009": {"function": {"delta": "20", "convention": "stdcall"}, "ordinal": "1009"}}}}