{"config": {"exports": {"NTSDEXTS.dll:winntflags": {"function": {"delta": "16", "convention": "stdcall"}, "ordinal": "12"}, "NTSDEXTS.dll:winntstr": {"function": {"delta": "16", "convention": "stdcall"}, "ordinal": "13"}, "NTSDEXTS.dll:st": {"function": {"delta": "16", "convention": "stdcall"}, "ordinal": "9"}, "NTSDEXTS.dll:queue": {"function": {"delta": "16", "convention": "stdcall"}, "ordinal": "7"}, "NTSDEXTS.dll:ocm": {"function": {"delta": "16", "convention": "stdcall"}, "ordinal": "5"}, "NTSDEXTS.dll:error": {"function": {"delta": "16", "convention": "stdcall"}, "ordinal": "1"}, "NTSDEXTS.dll:infdump": {"function": {"delta": "16", "convention": "stdcall"}, "ordinal": "4"}, "NTSDEXTS.dll:gle": {"function": {"delta": "16", "convention": "stdcall"}, "ordinal": "2"}, "NTSDEXTS.dll:stfind": {"function": {"delta": "16", "convention": "stdcall"}, "ordinal": "10"}, "NTSDEXTS.dll:space": {"function": {"delta": "16", "convention": "stdcall"}, "ordinal": "8"}, "NTSDEXTS.dll:version": {"function": {"delta": "16", "convention": "stdcall"}, "ordinal": "11"}, "NTSDEXTS.dll:qcontext": {"function": {"delta": "16", "convention": "stdcall"}, "ordinal": "6"}, "NTSDEXTS.dll:help": {"function": {"delta": "16", "convention": "stdcall"}, "ordinal": "3"}}}}