{"config": {"exports": {"OLEAUT32.dll:GetVarConversionLocaleSetting": {"function": {"delta": "0", "convention": "stdcall"}, "ordinal": "326"}, "OLEAUT32.dll:RegisterTypeLib": {"function": {"delta": "8", "convention": "stdcall"}, "ordinal": "163"}, "OLEAUT32.dll:GetAltMonthNames": {"function": {"delta": "4", "convention": "stdcall"}, "ordinal": "332"}, "OLEAUT32.dll:LoadTypeLibEx": {"function": {"delta": "8", "convention": "stdcall"}, "ordinal": "183"}, "OLEAUT32.dll:LPSAFEARRAY_Unmarshal": {"function": {"delta": "12", "convention": "stdcall"}, "ordinal": "297"}, "OLEAUT32.dll:VarI1FromR8": {"function": {"delta": "8", "convention": "stdcall"}, "ordinal": "248"}, "OLEAUT32.dll:VarNeg": {"function": {"delta": "4", "convention": "stdcall"}, "ordinal": "173"}, "OLEAUT32.dll:OleLoadPicture": {"function": {"delta": "16", "convention": "stdcall"}, "ordinal": "418"}, "OLEAUT32.dll:VarI1FromR4": {"function": {"delta": "4", "convention": "stdcall"}, "ordinal": "247"}, "OLEAUT32.dll:SafeArrayCreateEx": {"function": {"delta": "12", "convention": "stdcall"}, "ordinal": "42"}, "OLEAUT32.dll:SafeArrayCopyData": {"function": {"delta": "4", "convention": "stdcall"}, "ordinal": "412"}, "OLEAUT32.dll:VarUI4FromStr": {"function": {"delta": "12", "convention": "stdcall"}, "ordinal": "277"}, "OLEAUT32.dll:VarUI4FromI8": {"function": {"delta": "8", "convention": "stdcall"}, "ordinal": "425"}, "OLEAUT32.dll:VarUI4FromI4": {"function": {"delta": "4", "convention": "stdcall"}, "ordinal": "272"}, "OLEAUT32.dll:VarUI4FromI1": {"function": {"delta": "4", "convention": "stdcall"}, "ordinal": "280"}, "OLEAUT32.dll:VarUI4FromI2": {"function": {"delta": "4", "convention": "stdcall"}, "ordinal": "271"}, "OLEAUT32.dll:VarR8Round": {"function": {"delta": "12", "convention": "stdcall"}, "ordinal": "317"}, "OLEAUT32.dll:VarBstrFromUI8": {"function": {"delta": "16", "convention": "stdcall"}, "ordinal": "369"}, "OLEAUT32.dll:VarBstrFromUI4": {"function": {"delta": "12", "convention": "stdcall"}, "ordinal": "231"}, "OLEAUT32.dll:VarBstrFromUI1": {"function": {"delta": "12", "convention": "stdcall"}, "ordinal": "108"}, "OLEAUT32.dll:VarBstrFromUI2": {"function": {"delta": "12", "convention": "stdcall"}, "ordinal": "230"}, "OLEAUT32.dll:VarI2FromDec": {"function": {"delta": "4", "convention": "stdcall"}, "ordinal": "208"}, "OLEAUT32.dll:VarDecCmp": {"function": {"delta": "4", "convention": "stdcall"}, "ordinal": "204"}, "OLEAUT32.dll:VarDateFromUdateEx": {"function": {"delta": "12", "convention": "stdcall"}, "ordinal": "319"}, "OLEAUT32.dll:VarOr": {"function": {"delta": "8", "convention": "stdcall"}, "ordinal": "157"}, "OLEAUT32.dll:VarMonthName": {"function": {"delta": "12", "convention": "stdcall"}, "ordinal": "129"}, "OLEAUT32.dll:VarUI8FromBool": {"function": {"delta": "4", "convention": "stdcall"}, "ordinal": "437"}, "OLEAUT32.dll:VarBstrCmp": {"function": {"delta": "12", "convention": "stdcall"}, "ordinal": "314"}, "OLEAUT32.dll:LHashValOfNameSysA": {"function": {"delta": "8", "convention": "stdcall"}, "ordinal": "166"}, "OLEAUT32.dll:VarR8FromR4": {"function": {"delta": "4", "convention": "stdcall"}, "ordinal": "81"}, "OLEAUT32.dll:VarBoolFromI8": {"function": {"delta": "8", "convention": "stdcall"}, "ordinal": "370"}, "OLEAUT32.dll:VarFix": {"function": {"delta": "4", "convention": "stdcall"}, "ordinal": "169"}, "OLEAUT32.dll:VariantChangeTypeEx": {"function": {"delta": "16", "convention": "stdcall"}, "ordinal": "147"}, "OLEAUT32.dll:VarUI2FromDisp": {"function": {"delta": "8", "convention": "stdcall"}, "ordinal": "265"}, "OLEAUT32.dll:VariantTimeToDosDateTime": {"function": {"delta": "12", "convention": "stdcall"}, "ordinal": "13"}, "OLEAUT32.dll:VarImp": {"function": {"delta": "8", "convention": "stdcall"}, "ordinal": "154"}, "OLEAUT32.dll:VarBoolFromI2": {"function": {"delta": "4", "convention": "stdcall"}, "ordinal": "119"}, "OLEAUT32.dll:VarBoolFromI4": {"function": {"delta": "4", "convention": "stdcall"}, "ordinal": "120"}, "OLEAUT32.dll:GetRecordInfoFromGuids": {"function": {"delta": "20", "convention": "stdcall"}, "ordinal": "322"}, "OLEAUT32.dll:VarBstrFromDisp": {"function": {"delta": "12", "convention": "stdcall"}, "ordinal": "115"}, "OLEAUT32.dll:VarR8Pow": {"function": {"delta": "16", "convention": "stdcall"}, "ordinal": "315"}, "OLEAUT32.dll:VarI1FromBool": {"function": {"delta": "4", "convention": "stdcall"}, "ordinal": "253"}, "OLEAUT32.dll:VarDecFromI1": {"function": {"delta": "4", "convention": "stdcall"}, "ordinal": "241"}, "OLEAUT32.dll:VarDecFromI4": {"function": {"delta": "4", "convention": "stdcall"}, "ordinal": "192"}, "OLEAUT32.dll:VarDecFromI8": {"function": {"delta": "8", "convention": "stdcall"}, "ordinal": "374"}, "OLEAUT32.dll:CreateDispTypeInfo": {"function": {"delta": "8", "convention": "stdcall"}, "ordinal": "31"}, "OLEAUT32.dll:VarDateFromI8": {"function": {"delta": "8", "convention": "stdcall"}, "ordinal": "364"}, "OLEAUT32.dll:VarCyCmpR8": {"function": {"delta": "12", "convention": "stdcall"}, "ordinal": "312"}, "OLEAUT32.dll:VarDateFromCy": {"function": {"delta": "8", "convention": "stdcall"}, "ordinal": "93"}, "OLEAUT32.dll:VariantClear": {"function": {"delta": "0", "convention": "stdcall"}, "ordinal": "9"}, "OLEAUT32.dll:GetActiveObject": {"function": {"delta": "8", "convention": "stdcall"}, "ordinal": "35"}, "OLEAUT32.dll:VarCyFromBool": {"function": {"delta": "4", "convention": "stdcall"}, "ordinal": "106"}, "OLEAUT32.dll:VarCyAdd": {"function": {"delta": "16", "convention": "stdcall"}, "ordinal": "299"}, "OLEAUT32.dll:OleLoadPictureFileEx": {"function": {"delta": "28", "convention": "stdcall"}, "ordinal": "402"}, "OLEAUT32.dll:VarI8FromCy": {"function": {"delta": "8", "convention": "stdcall"}, "ordinal": "337"}, "OLEAUT32.dll:VarDecFix": {"function": {"delta": "4", "convention": "stdcall"}, "ordinal": "187"}, "OLEAUT32.dll:VarI8FromDate": {"function": {"delta": "8", "convention": "stdcall"}, "ordinal": "338"}, "OLEAUT32.dll:VarBoolFromR4": {"function": {"delta": "4", "convention": "stdcall"}, "ordinal": "121"}, "OLEAUT32.dll:VarBoolFromR8": {"function": {"delta": "8", "convention": "stdcall"}, "ordinal": "122"}, "OLEAUT32.dll:VarIdiv": {"function": {"delta": "8", "convention": "stdcall"}, "ordinal": "153"}, "OLEAUT32.dll:VarUI8FromR8": {"function": {"delta": "8", "convention": "stdcall"}, "ordinal": "432"}, "OLEAUT32.dll:VarDateFromDisp": {"function": {"delta": "8", "convention": "stdcall"}, "ordinal": "95"}, "OLEAUT32.dll:VarDecFromDate": {"function": {"delta": "8", "convention": "stdcall"}, "ordinal": "195"}, "OLEAUT32.dll:SafeArraySetRecordInfo": {"function": {"delta": "4", "convention": "stdcall"}, "ordinal": "44"}, "OLEAUT32.dll:VarUI8FromR4": {"function": {"delta": "4", "convention": "stdcall"}, "ordinal": "431"}, "OLEAUT32.dll:VarUI1FromUI8": {"function": {"delta": "8", "convention": "stdcall"}, "ordinal": "373"}, "OLEAUT32.dll:VarUI1FromUI4": {"function": {"delta": "4", "convention": "stdcall"}, "ordinal": "239"}, "OLEAUT32.dll:VarUI1FromUI2": {"function": {"delta": "4", "convention": "stdcall"}, "ordinal": "238"}, "OLEAUT32.dll:VarR8FromDisp": {"function": {"delta": "8", "convention": "stdcall"}, "ordinal": "85"}, "OLEAUT32.dll:VarUI8FromDec": {"function": {"delta": "4", "convention": "stdcall"}, "ordinal": "441"}, "OLEAUT32.dll:VarUI2FromR4": {"function": {"delta": "4", "convention": "stdcall"}, "ordinal": "260"}, "OLEAUT32.dll:OleCreatePropertyFrame": {"function": {"delta": "40", "convention": "stdcall"}, "ordinal": "417"}, "OLEAUT32.dll:VARIANT_UserSize": {"function": {"delta": "8", "convention": "stdcall"}, "ordinal": "287"}, "OLEAUT32.dll:VarUI2FromR8": {"function": {"delta": "8", "convention": "stdcall"}, "ordinal": "261"}, "OLEAUT32.dll:VarDiv": {"function": {"delta": "8", "convention": "stdcall"}, "ordinal": "143"}, "OLEAUT32.dll:VarI2FromR8": {"function": {"delta": "8", "convention": "stdcall"}, "ordinal": "51"}, "OLEAUT32.dll:VarI2FromR4": {"function": {"delta": "4", "convention": "stdcall"}, "ordinal": "50"}, "OLEAUT32.dll:VarI8FromDec": {"function": {"delta": "4", "convention": "stdcall"}, "ordinal": "345"}, "OLEAUT32.dll:VarI8FromDisp": {"function": {"delta": "8", "convention": "stdcall"}, "ordinal": "340"}, "OLEAUT32.dll:VarUI2FromI8": {"function": {"delta": "8", "convention": "stdcall"}, "ordinal": "378"}, "OLEAUT32.dll:SafeArrayDestroyData": {"function": {"delta": "0", "convention": "stdcall"}, "ordinal": "39"}, "OLEAUT32.dll:VarUI2FromI2": {"function": {"delta": "4", "convention": "stdcall"}, "ordinal": "258"}, "OLEAUT32.dll:OleCreateFontIndirect": {"function": {"delta": "8", "convention": "stdcall"}, "ordinal": "420"}, "OLEAUT32.dll:VarUI2FromI1": {"function": {"delta": "4", "convention": "stdcall"}, "ordinal": "267"}, "OLEAUT32.dll:VarUI2FromI4": {"function": {"delta": "4", "convention": "stdcall"}, "ordinal": "259"}, "OLEAUT32.dll:VarFormatFromTokens": {"function": {"delta": "20", "convention": "stdcall"}, "ordinal": "139"}, "OLEAUT32.dll:VarUI2FromUI1": {"function": {"delta": "4", "convention": "stdcall"}, "ordinal": "257"}, "OLEAUT32.dll:VarUI2FromUI4": {"function": {"delta": "4", "convention": "stdcall"}, "ordinal": "268"}, "OLEAUT32.dll:VarR4FromDec": {"function": {"delta": "4", "convention": "stdcall"}, "ordinal": "216"}, "OLEAUT32.dll:RegisterTypeLibForUser": {"function": {"delta": "8", "convention": "stdcall"}, "ordinal": "442"}, "OLEAUT32.dll:SafeArrayRedim": {"function": {"delta": "4", "convention": "stdcall"}, "ordinal": "40"}, "OLEAUT32.dll:VarUI4FromDate": {"function": {"delta": "8", "convention": "stdcall"}, "ordinal": "275"}, "OLEAUT32.dll:SafeArrayAllocData": {"function": {"delta": "0", "convention": "stdcall"}, "ordinal": "37"}, "OLEAUT32.dll:VarUI2FromCy": {"function": {"delta": "8", "convention": "stdcall"}, "ordinal": "263"}, "OLEAUT32.dll:VARIANT_UserUnmarshal": {"function": {"delta": "8", "convention": "stdcall"}, "ordinal": "289"}, "OLEAUT32.dll:VarBstrCat": {"function": {"delta": "8", "convention": "stdcall"}, "ordinal": "313"}, "OLEAUT32.dll:VarCyNeg": {"function": {"delta": "8", "convention": "stdcall"}, "ordinal": "309"}, "OLEAUT32.dll:VarI2FromStr": {"function": {"delta": "12", "convention": "stdcall"}, "ordinal": "54"}, "OLEAUT32.dll:OleTranslateColor": {"function": {"delta": "8", "convention": "stdcall"}, "ordinal": "421"}, "OLEAUT32.dll:VarDecFromStr": {"function": {"delta": "12", "convention": "stdcall"}, "ordinal": "197"}, "OLEAUT32.dll:VarUI4FromUI2": {"function": {"delta": "4", "convention": "stdcall"}, "ordinal": "281"}, "OLEAUT32.dll:VarI2FromBool": {"function": {"delta": "4", "convention": "stdcall"}, "ordinal": "56"}, "OLEAUT32.dll:VarRound": {"function": {"delta": "8", "convention": "stdcall"}, "ordinal": "175"}, "OLEAUT32.dll:VarUI4FromUI8": {"function": {"delta": "8", "convention": "stdcall"}, "ordinal": "426"}, "OLEAUT32.dll:LPSAFEARRAY_Marshal": {"function": {"delta": "12", "convention": "stdcall"}, "ordinal": "296"}, "OLEAUT32.dll:VarI1FromUI8": {"function": {"delta": "8", "convention": "stdcall"}, "ordinal": "377"}, "OLEAUT32.dll:VarCmp": {"function": {"delta": "12", "convention": "stdcall"}, "ordinal": "176"}, "OLEAUT32.dll:VarI4FromDec": {"function": {"delta": "4", "convention": "stdcall"}, "ordinal": "212"}, "OLEAUT32.dll:VarI1FromUI4": {"function": {"delta": "4", "convention": "stdcall"}, "ordinal": "255"}, "OLEAUT32.dll:VarI1FromUI1": {"function": {"delta": "4", "convention": "stdcall"}, "ordinal": "244"}, "OLEAUT32.dll:VarI1FromUI2": {"function": {"delta": "4", "convention": "stdcall"}, "ordinal": "254"}, "OLEAUT32.dll:VarR4FromDate": {"function": {"delta": "8", "convention": "stdcall"}, "ordinal": "73"}, "OLEAUT32.dll:GetRecordInfoFromTypeInfo": {"function": {"delta": "4", "convention": "stdcall"}, "ordinal": "323"}, "OLEAUT32.dll:VarDecAdd": {"function": {"delta": "8", "convention": "stdcall"}, "ordinal": "177"}, "OLEAUT32.dll:VectorFromBstr": {"function": {"delta": "4", "convention": "stdcall"}, "ordinal": "413"}, "OLEAUT32.dll:VarDateFromStr": {"function": {"delta": "12", "convention": "stdcall"}, "ordinal": "94"}, "OLEAUT32.dll:LPSAFEARRAY_UserSize": {"function": {"delta": "8", "convention": "stdcall"}, "ordinal": "291"}, "OLEAUT32.dll:DispGetIDsOfNames": {"function": {"delta": "12", "convention": "stdcall"}, "ordinal": "29"}, "OLEAUT32.dll:VarR4FromBool": {"function": {"delta": "4", "convention": "stdcall"}, "ordinal": "76"}, "OLEAUT32.dll:VarI4FromBool": {"function": {"delta": "4", "convention": "stdcall"}, "ordinal": "66"}, "OLEAUT32.dll:SysAllocString": {"function": {"delta": "0", "convention": "stdcall"}, "ordinal": "2"}, "OLEAUT32.dll:VarUI1FromDate": {"function": {"delta": "8", "convention": "stdcall"}, "ordinal": "135"}, "OLEAUT32.dll:VarI8FromI1": {"function": {"delta": "4", "convention": "stdcall"}, "ordinal": "342"}, "OLEAUT32.dll:VarI8FromI2": {"function": {"delta": "4", "convention": "stdcall"}, "ordinal": "334"}, "OLEAUT32.dll:CreateTypeLib2": {"function": {"delta": "8", "convention": "stdcall"}, "ordinal": "180"}, "OLEAUT32.dll:SysStringLen": {"function": {"delta": "0", "convention": "stdcall"}, "ordinal": "7"}, "OLEAUT32.dll:VarR8FromI2": {"function": {"delta": "4", "convention": "stdcall"}, "ordinal": "79"}, "OLEAUT32.dll:VarNumFromParseNum": {"function": {"delta": "12", "convention": "stdcall"}, "ordinal": "47"}, "OLEAUT32.dll:VarUI2FromUI8": {"function": {"delta": "8", "convention": "stdcall"}, "ordinal": "379"}, "OLEAUT32.dll:VarUI8FromDisp": {"function": {"delta": "8", "convention": "stdcall"}, "ordinal": "436"}, "OLEAUT32.dll:VarBstrFromBool": {"function": {"delta": "12", "convention": "stdcall"}, "ordinal": "116"}, "OLEAUT32.dll:VarCyInt": {"function": {"delta": "8", "convention": "stdcall"}, "ordinal": "308"}, "OLEAUT32.dll:RegisterActiveObject": {"function": {"delta": "12", "convention": "stdcall"}, "ordinal": "33"}, "OLEAUT32.dll:VarR8FromDate": {"function": {"delta": "8", "convention": "stdcall"}, "ordinal": "83"}, "OLEAUT32.dll:VarDateFromR8": {"function": {"delta": "8", "convention": "stdcall"}, "ordinal": "92"}, "OLEAUT32.dll:VarDateFromR4": {"function": {"delta": "4", "convention": "stdcall"}, "ordinal": "91"}, "OLEAUT32.dll:RevokeActiveObject": {"function": {"delta": "4", "convention": "stdcall"}, "ordinal": "34"}, "OLEAUT32.dll:VarBstrFromI8": {"function": {"delta": "16", "convention": "stdcall"}, "ordinal": "368"}, "OLEAUT32.dll:VarBstrFromI2": {"function": {"delta": "12", "convention": "stdcall"}, "ordinal": "109"}, "OLEAUT32.dll:CreateErrorInfo": {"function": {"delta": "0", "convention": "stdcall"}, "ordinal": "202"}, "OLEAUT32.dll:VarBstrFromI1": {"function": {"delta": "12", "convention": "stdcall"}, "ordinal": "229"}, "OLEAUT32.dll:VarBstrFromI4": {"function": {"delta": "12", "convention": "stdcall"}, "ordinal": "110"}, "OLEAUT32.dll:VarUI1FromR8": {"function": {"delta": "8", "convention": "stdcall"}, "ordinal": "133"}, "OLEAUT32.dll:LPSAFEARRAY_Size": {"function": {"delta": "12", "convention": "stdcall"}, "ordinal": "295"}, "OLEAUT32.dll:SafeArrayPtrOfIndex": {"function": {"delta": "8", "convention": "stdcall"}, "ordinal": "148"}, "OLEAUT32.dll:VarUI1FromR4": {"function": {"delta": "4", "convention": "stdcall"}, "ordinal": "132"}, "OLEAUT32.dll:VarDateFromUdate": {"function": {"delta": "8", "convention": "stdcall"}, "ordinal": "330"}, "OLEAUT32.dll:VarDecFromUI8": {"function": {"delta": "8", "convention": "stdcall"}, "ordinal": "375"}, "OLEAUT32.dll:BstrFromVector": {"function": {"delta": "4", "convention": "stdcall"}, "ordinal": "414"}, "OLEAUT32.dll:BSTR_UserMarshal": {"function": {"delta": "8", "convention": "stdcall"}, "ordinal": "284"}, "OLEAUT32.dll:SafeArrayGetVartype": {"function": {"delta": "4", "convention": "stdcall"}, "ordinal": "77"}, "OLEAUT32.dll:VarDecDiv": {"function": {"delta": "8", "convention": "stdcall"}, "ordinal": "178"}, "OLEAUT32.dll:SafeArrayGetDim": {"function": {"delta": "0", "convention": "stdcall"}, "ordinal": "17"}, "OLEAUT32.dll:SafeArrayDestroyDescriptor": {"function": {"delta": "0", "convention": "stdcall"}, "ordinal": "38"}, "OLEAUT32.dll:VarFormatCurrency": {"function": {"delta": "24", "convention": "stdcall"}, "ordinal": "127"}, "OLEAUT32.dll:VarI2FromUI8": {"function": {"delta": "8", "convention": "stdcall"}, "ordinal": "347"}, "OLEAUT32.dll:LoadTypeLib": {"function": {"delta": "4", "convention": "stdcall"}, "ordinal": "161"}, "OLEAUT32.dll:LPSAFEARRAY_UserFree": {"function": {"delta": "4", "convention": "stdcall"}, "ordinal": "294"}, "OLEAUT32.dll:VarI8FromUI8": {"function": {"delta": "8", "convention": "stdcall"}, "ordinal": "427"}, "OLEAUT32.dll:VarDecFromCy": {"function": {"delta": "8", "convention": "stdcall"}, "ordinal": "196"}, "OLEAUT32.dll:VarI8FromUI4": {"function": {"delta": "4", "convention": "stdcall"}, "ordinal": "344"}, "OLEAUT32.dll:VarI8FromUI2": {"function": {"delta": "4", "convention": "stdcall"}, "ordinal": "343"}, "OLEAUT32.dll:VarI8FromUI1": {"function": {"delta": "4", "convention": "stdcall"}, "ordinal": "333"}, "OLEAUT32.dll:VarI2FromUI4": {"function": {"delta": "4", "convention": "stdcall"}, "ordinal": "207"}, "OLEAUT32.dll:VariantInit": {"function": {"delta": "0", "convention": "stdcall"}, "ordinal": "8"}, "OLEAUT32.dll:VarUI8FromUI2": {"function": {"delta": "4", "convention": "stdcall"}, "ordinal": "439"}, "OLEAUT32.dll:OleIconToCursor": {"function": {"delta": "4", "convention": "stdcall"}, "ordinal": "415"}, "OLEAUT32.dll:VarR4FromUI4": {"function": {"delta": "4", "convention": "stdcall"}, "ordinal": "215"}, "OLEAUT32.dll:VarFormatNumber": {"function": {"delta": "24", "convention": "stdcall"}, "ordinal": "107"}, "OLEAUT32.dll:DispGetParam": {"function": {"delta": "16", "convention": "stdcall"}, "ordinal": "28"}, "OLEAUT32.dll:VarR4FromUI1": {"function": {"delta": "4", "convention": "stdcall"}, "ordinal": "68"}, "OLEAUT32.dll:VarR4FromUI2": {"function": {"delta": "4", "convention": "stdcall"}, "ordinal": "214"}, "OLEAUT32.dll:VarR4FromUI8": {"function": {"delta": "8", "convention": "stdcall"}, "ordinal": "361"}, "OLEAUT32.dll:VarR8FromUI4": {"function": {"delta": "4", "convention": "stdcall"}, "ordinal": "219"}, "OLEAUT32.dll:DispInvoke": {"function": {"delta": "28", "convention": "stdcall"}, "ordinal": "30"}, "OLEAUT32.dll:OleSavePictureFile": {"function": {"delta": "4", "convention": "stdcall"}, "ordinal": "423"}, "OLEAUT32.dll:VarUI8FromUI4": {"function": {"delta": "4", "convention": "stdcall"}, "ordinal": "440"}, "OLEAUT32.dll:VarI4FromUI2": {"function": {"delta": "4", "convention": "stdcall"}, "ordinal": "210"}, "OLEAUT32.dll:VarI4FromUI1": {"function": {"delta": "4", "convention": "stdcall"}, "ordinal": "58"}, "OLEAUT32.dll:SysReAllocString": {"function": {"delta": "4", "convention": "stdcall"}, "ordinal": "3"}, "OLEAUT32.dll:VarI4FromUI4": {"function": {"delta": "4", "convention": "stdcall"}, "ordinal": "211"}, "OLEAUT32.dll:VarUI8FromDate": {"function": {"delta": "8", "convention": "stdcall"}, "ordinal": "434"}, "OLEAUT32.dll:VarI4FromUI8": {"function": {"delta": "8", "convention": "stdcall"}, "ordinal": "349"}, "OLEAUT32.dll:BSTR_UserUnmarshal": {"function": {"delta": "8", "convention": "stdcall"}, "ordinal": "285"}, "OLEAUT32.dll:VarUI2FromBool": {"function": {"delta": "4", "convention": "stdcall"}, "ordinal": "266"}, "OLEAUT32.dll:VarCyMul": {"function": {"delta": "16", "convention": "stdcall"}, "ordinal": "303"}, "OLEAUT32.dll:VarUI8FromUI1": {"function": {"delta": "4", "convention": "stdcall"}, "ordinal": "429"}, "OLEAUT32.dll:VarR8FromBool": {"function": {"delta": "4", "convention": "stdcall"}, "ordinal": "86"}, "OLEAUT32.dll:VarR4FromCy": {"function": {"delta": "8", "convention": "stdcall"}, "ordinal": "72"}, "OLEAUT32.dll:VarR4FromStr": {"function": {"delta": "12", "convention": "stdcall"}, "ordinal": "74"}, "OLEAUT32.dll:VarDateFromBool": {"function": {"delta": "4", "convention": "stdcall"}, "ordinal": "96"}, "OLEAUT32.dll:VarCyAbs": {"function": {"delta": "8", "convention": "stdcall"}, "ordinal": "306"}, "OLEAUT32.dll:VarSub": {"function": {"delta": "8", "convention": "stdcall"}, "ordinal": "159"}, "OLEAUT32.dll:SafeArrayAccessData": {"function": {"delta": "4", "convention": "stdcall"}, "ordinal": "23"}, "OLEAUT32.dll:VarDecMul": {"function": {"delta": "8", "convention": "stdcall"}, "ordinal": "179"}, "OLEAUT32.dll:VarCyRound": {"function": {"delta": "12", "convention": "stdcall"}, "ordinal": "310"}, "OLEAUT32.dll:VarUI1FromDisp": {"function": {"delta": "8", "convention": "stdcall"}, "ordinal": "137"}, "OLEAUT32.dll:VarCyCmp": {"function": {"delta": "12", "convention": "stdcall"}, "ordinal": "311"}, "OLEAUT32.dll:SafeArrayCreateVectorEx": {"function": {"delta": "12", "convention": "stdcall"}, "ordinal": "43"}, "OLEAUT32.dll:SetErrorInfo": {"function": {"delta": "4", "convention": "stdcall"}, "ordinal": "201"}, "OLEAUT32.dll:VarBoolFromDisp": {"function": {"delta": "8", "convention": "stdcall"}, "ordinal": "126"}, "OLEAUT32.dll:VarDecRound": {"function": {"delta": "8", "convention": "stdcall"}, "ordinal": "203"}, "OLEAUT32.dll:VarI8FromBool": {"function": {"delta": "4", "convention": "stdcall"}, "ordinal": "341"}, "OLEAUT32.dll:VarUI2FromDec": {"function": {"delta": "4", "convention": "stdcall"}, "ordinal": "269"}, "OLEAUT32.dll:VarTokenizeFormatString": {"function": {"delta": "24", "convention": "stdcall"}, "ordinal": "140"}, "OLEAUT32.dll:LoadRegTypeLib": {"function": {"delta": "16", "convention": "stdcall"}, "ordinal": "162"}, "OLEAUT32.dll:VariantTimeToSystemTime": {"function": {"delta": "8", "convention": "stdcall"}, "ordinal": "185"}, "OLEAUT32.dll:VarEqv": {"function": {"delta": "8", "convention": "stdcall"}, "ordinal": "152"}, "OLEAUT32.dll:CreateStdDispatch": {"function": {"delta": "12", "convention": "stdcall"}, "ordinal": "32"}, "OLEAUT32.dll:OleCreatePropertyFrameIndirect": {"function": {"delta": "0", "convention": "stdcall"}, "ordinal": "416"}, "OLEAUT32.dll:VarUI1FromCy": {"function": {"delta": "8", "convention": "stdcall"}, "ordinal": "134"}, "OLEAUT32.dll:SafeArrayLock": {"function": {"delta": "0", "convention": "stdcall"}, "ordinal": "21"}, "OLEAUT32.dll:LPSAFEARRAY_UserMarshal": {"function": {"delta": "8", "convention": "stdcall"}, "ordinal": "292"}, "OLEAUT32.dll:VarI2FromDisp": {"function": {"delta": "8", "convention": "stdcall"}, "ordinal": "55"}, "OLEAUT32.dll:SafeArrayUnaccessData": {"function": {"delta": "0", "convention": "stdcall"}, "ordinal": "24"}, "OLEAUT32.dll:VARIANT_UserMarshal": {"function": {"delta": "8", "convention": "stdcall"}, "ordinal": "288"}, "OLEAUT32.dll:VarI4FromDate": {"function": {"delta": "8", "convention": "stdcall"}, "ordinal": "63"}, "OLEAUT32.dll:VarUI4FromUI1": {"function": {"delta": "4", "convention": "stdcall"}, "ordinal": "270"}, "OLEAUT32.dll:VarMod": {"function": {"delta": "8", "convention": "stdcall"}, "ordinal": "155"}, "OLEAUT32.dll:CreateTypeLib": {"function": {"delta": "8", "convention": "stdcall"}, "ordinal": "160"}, "OLEAUT32.dll:SysReAllocStringLen": {"function": {"delta": "8", "convention": "stdcall"}, "ordinal": "5"}, "OLEAUT32.dll:SafeArrayDestroy": {"function": {"delta": "0", "convention": "stdcall"}, "ordinal": "16"}, "OLEAUT32.dll:VarR8FromUI8": {"function": {"delta": "8", "convention": "stdcall"}, "ordinal": "363"}, "OLEAUT32.dll:VarCyFix": {"function": {"delta": "8", "convention": "stdcall"}, "ordinal": "307"}, "OLEAUT32.dll:VarR8FromUI1": {"function": {"delta": "4", "convention": "stdcall"}, "ordinal": "78"}, "OLEAUT32.dll:VarDecFromUI1": {"function": {"delta": "4", "convention": "stdcall"}, "ordinal": "190"}, "OLEAUT32.dll:VarDecFromUI2": {"function": {"delta": "4", "convention": "stdcall"}, "ordinal": "242"}, "OLEAUT32.dll:VarR8FromUI2": {"function": {"delta": "4", "convention": "stdcall"}, "ordinal": "218"}, "OLEAUT32.dll:VarDecFromUI4": {"function": {"delta": "4", "convention": "stdcall"}, "ordinal": "243"}, "OLEAUT32.dll:VarI2FromUI1": {"function": {"delta": "4", "convention": "stdcall"}, "ordinal": "48"}, "OLEAUT32.dll:VarI2FromUI2": {"function": {"delta": "4", "convention": "stdcall"}, "ordinal": "206"}, "OLEAUT32.dll:VariantChangeType": {"function": {"delta": "12", "convention": "stdcall"}, "ordinal": "12"}, "OLEAUT32.dll:VarPow": {"function": {"delta": "8", "convention": "stdcall"}, "ordinal": "158"}, "OLEAUT32.dll:VarDecFromDisp": {"function": {"delta": "8", "convention": "stdcall"}, "ordinal": "198"}, "OLEAUT32.dll:VarDecAbs": {"function": {"delta": "4", "convention": "stdcall"}, "ordinal": "182"}, "OLEAUT32.dll:CStrToD": {"function": {"delta": "0", "convention": "stdcall"}, "ordinal": "144"}, "OLEAUT32.dll:VarFormat": {"function": {"delta": "20", "convention": "stdcall"}, "ordinal": "87"}, "OLEAUT32.dll:VarBoolFromUI1": {"function": {"delta": "4", "convention": "stdcall"}, "ordinal": "118"}, "OLEAUT32.dll:VarBoolFromUI2": {"function": {"delta": "4", "convention": "stdcall"}, "ordinal": "234"}, "OLEAUT32.dll:VarBoolFromUI4": {"function": {"delta": "4", "convention": "stdcall"}, "ordinal": "235"}, "OLEAUT32.dll:VarBoolFromUI8": {"function": {"delta": "8", "convention": "stdcall"}, "ordinal": "371"}, "OLEAUT32.dll:UnRegisterTypeLib": {"function": {"delta": "16", "convention": "stdcall"}, "ordinal": "186"}, "OLEAUT32.dll:VarI1FromI8": {"function": {"delta": "8", "convention": "stdcall"}, "ordinal": "376"}, "OLEAUT32.dll:VarI1FromI2": {"function": {"delta": "4", "convention": "stdcall"}, "ordinal": "245"}, "OLEAUT32.dll:VarI1FromI4": {"function": {"delta": "4", "convention": "stdcall"}, "ordinal": "246"}, "OLEAUT32.dll:VarFormatPercent": {"function": {"delta": "24", "convention": "stdcall"}, "ordinal": "117"}, "OLEAUT32.dll:VarUI2FromStr": {"function": {"delta": "12", "convention": "stdcall"}, "ordinal": "264"}, "OLEAUT32.dll:UnRegisterTypeLibForUser": {"function": {"delta": "16", "convention": "stdcall"}, "ordinal": "443"}, "OLEAUT32.dll:VarUI1FromStr": {"function": {"delta": "12", "convention": "stdcall"}, "ordinal": "136"}, "OLEAUT32.dll:VarDecFromR8": {"function": {"delta": "8", "convention": "stdcall"}, "ordinal": "194"}, "OLEAUT32.dll:VarDecFromR4": {"function": {"delta": "4", "convention": "stdcall"}, "ordinal": "193"}, "OLEAUT32.dll:VarXor": {"function": {"delta": "8", "convention": "stdcall"}, "ordinal": "167"}, "OLEAUT32.dll:VarI4FromI8": {"function": {"delta": "8", "convention": "stdcall"}, "ordinal": "348"}, "OLEAUT32.dll:VarI4FromI1": {"function": {"delta": "4", "convention": "stdcall"}, "ordinal": "209"}, "OLEAUT32.dll:VarI4FromI2": {"function": {"delta": "4", "convention": "stdcall"}, "ordinal": "59"}, "OLEAUT32.dll:VarWeekdayName": {"function": {"delta": "16", "convention": "stdcall"}, "ordinal": "128"}, "OLEAUT32.dll:SafeArrayGetElemsize": {"function": {"delta": "0", "convention": "stdcall"}, "ordinal": "18"}, "OLEAUT32.dll:VarBstrFromDec": {"function": {"delta": "12", "convention": "stdcall"}, "ordinal": "232"}, "OLEAUT32.dll:SysFreeString": {"function": {"delta": "0", "convention": "stdcall"}, "ordinal": "6"}, "OLEAUT32.dll:VARIANT_UserFree": {"function": {"delta": "4", "convention": "stdcall"}, "ordinal": "290"}, "OLEAUT32.dll:VarDecFromBool": {"function": {"delta": "4", "convention": "stdcall"}, "ordinal": "199"}, "OLEAUT32.dll:VarCyFromUI2": {"function": {"delta": "4", "convention": "stdcall"}, "ordinal": "226"}, "OLEAUT32.dll:VarCyFromUI1": {"function": {"delta": "4", "convention": "stdcall"}, "ordinal": "98"}, "OLEAUT32.dll:VarCyFromUI4": {"function": {"delta": "4", "convention": "stdcall"}, "ordinal": "227"}, "OLEAUT32.dll:VarCyFromUI8": {"function": {"delta": "8", "convention": "stdcall"}, "ordinal": "367"}, "OLEAUT32.dll:VarDecNeg": {"function": {"delta": "4", "convention": "stdcall"}, "ordinal": "189"}, "OLEAUT32.dll:OleLoadPictureEx": {"function": {"delta": "28", "convention": "stdcall"}, "ordinal": "401"}, "OLEAUT32.dll:DispCallFunc": {"function": {"delta": "28", "convention": "stdcall"}, "ordinal": "146"}, "OLEAUT32.dll:VarDateFromDec": {"function": {"delta": "4", "convention": "stdcall"}, "ordinal": "224"}, "OLEAUT32.dll:VarI4FromStr": {"function": {"delta": "12", "convention": "stdcall"}, "ordinal": "64"}, "OLEAUT32.dll:VarAdd": {"function": {"delta": "8", "convention": "stdcall"}, "ordinal": "141"}, "OLEAUT32.dll:VarCyFromDisp": {"function": {"delta": "8", "convention": "stdcall"}, "ordinal": "105"}, "OLEAUT32.dll:OACreateTypeLib2": {"function": {"delta": "8", "convention": "stdcall"}, "ordinal": "302"}, "OLEAUT32.dll:VarCySub": {"function": {"delta": "16", "convention": "stdcall"}, "ordinal": "305"}, "OLEAUT32.dll:SysAllocStringLen": {"function": {"delta": "4", "convention": "stdcall"}, "ordinal": "4"}, "OLEAUT32.dll:VarFormatDateTime": {"function": {"delta": "12", "convention": "stdcall"}, "ordinal": "97"}, "OLEAUT32.dll:SafeArraySetIID": {"function": {"delta": "4", "convention": "stdcall"}, "ordinal": "57"}, "OLEAUT32.dll:SetOaNoCache": {"function": {"delta": "-4", "convention": "stdcall"}, "ordinal": "327"}, "OLEAUT32.dll:VarI1FromDate": {"function": {"delta": "8", "convention": "stdcall"}, "ordinal": "249"}, "OLEAUT32.dll:VarDecFromI2": {"function": {"delta": "4", "convention": "stdcall"}, "ordinal": "191"}, "OLEAUT32.dll:SetVarConversionLocaleSetting": {"function": {"delta": "0", "convention": "stdcall"}, "ordinal": "325"}, "OLEAUT32.dll:VarBoolFromDate": {"function": {"delta": "8", "convention": "stdcall"}, "ordinal": "123"}, "OLEAUT32.dll:VarNot": {"function": {"delta": "4", "convention": "stdcall"}, "ordinal": "174"}, "OLEAUT32.dll:SafeArrayGetElement": {"function": {"delta": "8", "convention": "stdcall"}, "ordinal": "25"}, "OLEAUT32.dll:OaBuildVersion": {"function": {"delta": "-4", "convention": "stdcall"}, "ordinal": "170"}, "OLEAUT32.dll:VarUI4FromCy": {"function": {"delta": "8", "convention": "stdcall"}, "ordinal": "276"}, "OLEAUT32.dll:VarUI1FromBool": {"function": {"delta": "4", "convention": "stdcall"}, "ordinal": "138"}, "OLEAUT32.dll:VarI2FromI8": {"function": {"delta": "8", "convention": "stdcall"}, "ordinal": "346"}, "OLEAUT32.dll:VarI4FromR8": {"function": {"delta": "8", "convention": "stdcall"}, "ordinal": "61"}, "OLEAUT32.dll:VarI4FromR4": {"function": {"delta": "4", "convention": "stdcall"}, "ordinal": "60"}, "OLEAUT32.dll:VarI2FromI1": {"function": {"delta": "4", "convention": "stdcall"}, "ordinal": "205"}, "OLEAUT32.dll:VarI1FromDisp": {"function": {"delta": "8", "convention": "stdcall"}, "ordinal": "252"}, "OLEAUT32.dll:VarI2FromI4": {"function": {"delta": "4", "convention": "stdcall"}, "ordinal": "49"}, "OLEAUT32.dll:VarR8FromI4": {"function": {"delta": "4", "convention": "stdcall"}, "ordinal": "80"}, "OLEAUT32.dll:VarR8FromI1": {"function": {"delta": "4", "convention": "stdcall"}, "ordinal": "217"}, "OLEAUT32.dll:SafeArrayGetRecordInfo": {"function": {"delta": "4", "convention": "stdcall"}, "ordinal": "45"}, "OLEAUT32.dll:VarCyFromI4": {"function": {"delta": "4", "convention": "stdcall"}, "ordinal": "100"}, "OLEAUT32.dll:VarR8FromI8": {"function": {"delta": "8", "convention": "stdcall"}, "ordinal": "362"}, "OLEAUT32.dll:VarUI1FromI8": {"function": {"delta": "8", "convention": "stdcall"}, "ordinal": "372"}, "OLEAUT32.dll:VarR8FromDec": {"function": {"delta": "4", "convention": "stdcall"}, "ordinal": "220"}, "OLEAUT32.dll:VarUI1FromI1": {"function": {"delta": "4", "convention": "stdcall"}, "ordinal": "237"}, "OLEAUT32.dll:VarUI1FromI2": {"function": {"delta": "4", "convention": "stdcall"}, "ordinal": "130"}, "OLEAUT32.dll:VarUI1FromI4": {"function": {"delta": "4", "convention": "stdcall"}, "ordinal": "131"}, "OLEAUT32.dll:OleLoadPicturePath": {"function": {"delta": "20", "convention": "stdcall"}, "ordinal": "424"}, "OLEAUT32.dll:VarInt": {"function": {"delta": "4", "convention": "stdcall"}, "ordinal": "172"}, "OLEAUT32.dll:SafeArrayAllocDescriptorEx": {"function": {"delta": "8", "convention": "stdcall"}, "ordinal": "41"}, "OLEAUT32.dll:VarAnd": {"function": {"delta": "8", "convention": "stdcall"}, "ordinal": "142"}, "OLEAUT32.dll:VarDateFromUI4": {"function": {"delta": "4", "convention": "stdcall"}, "ordinal": "223"}, "OLEAUT32.dll:VarDateFromUI1": {"function": {"delta": "4", "convention": "stdcall"}, "ordinal": "88"}, "OLEAUT32.dll:DosDateTimeToVariantTime": {"function": {"delta": "8", "convention": "stdcall"}, "ordinal": "14"}, "OLEAUT32.dll:VarDateFromUI2": {"function": {"delta": "4", "convention": "stdcall"}, "ordinal": "222"}, "OLEAUT32.dll:VarDateFromUI8": {"function": {"delta": "8", "convention": "stdcall"}, "ordinal": "365"}, "OLEAUT32.dll:VarR4CmpR8": {"function": {"delta": "8", "convention": "stdcall"}, "ordinal": "316"}, "OLEAUT32.dll:VarUI1FromDec": {"function": {"delta": "4", "convention": "stdcall"}, "ordinal": "240"}, "OLEAUT32.dll:VarI1FromCy": {"function": {"delta": "8", "convention": "stdcall"}, "ordinal": "250"}, "OLEAUT32.dll:VarCyFromI8": {"function": {"delta": "8", "convention": "stdcall"}, "ordinal": "366"}, "OLEAUT32.dll:ClearCustData": {"function": {"delta": "0", "convention": "stdcall"}, "ordinal": "171"}, "OLEAUT32.dll:SafeArrayCopy": {"function": {"delta": "4", "convention": "stdcall"}, "ordinal": "27"}, "OLEAUT32.dll:VarCyFromI2": {"function": {"delta": "4", "convention": "stdcall"}, "ordinal": "99"}, "OLEAUT32.dll:VarCyFromI1": {"function": {"delta": "4", "convention": "stdcall"}, "ordinal": "225"}, "OLEAUT32.dll:SafeArrayPutElement": {"function": {"delta": "8", "convention": "stdcall"}, "ordinal": "26"}, "OLEAUT32.dll:VarParseNumFromStr": {"function": {"delta": "16", "convention": "stdcall"}, "ordinal": "46"}, "OLEAUT32.dll:VarI1FromStr": {"function": {"delta": "12", "convention": "stdcall"}, "ordinal": "251"}, "OLEAUT32.dll:VarUI4FromBool": {"function": {"delta": "4", "convention": "stdcall"}, "ordinal": "279"}, "OLEAUT32.dll:VarUI8FromI8": {"function": {"delta": "8", "convention": "stdcall"}, "ordinal": "428"}, "OLEAUT32.dll:VarUI4FromDisp": {"function": {"delta": "8", "convention": "stdcall"}, "ordinal": "278"}, "OLEAUT32.dll:VarUI8FromI2": {"function": {"delta": "4", "convention": "stdcall"}, "ordinal": "430"}, "OLEAUT32.dll:VarBoolFromI1": {"function": {"delta": "4", "convention": "stdcall"}, "ordinal": "233"}, "OLEAUT32.dll:LHashValOfNameSys": {"function": {"delta": "8", "convention": "stdcall"}, "ordinal": "165"}, "OLEAUT32.dll:VarCyMulI8": {"function": {"delta": "16", "convention": "stdcall"}, "ordinal": "329"}, "OLEAUT32.dll:SafeArrayUnlock": {"function": {"delta": "0", "convention": "stdcall"}, "ordinal": "22"}, "OLEAUT32.dll:VarI4FromDisp": {"function": {"delta": "8", "convention": "stdcall"}, "ordinal": "65"}, "OLEAUT32.dll:VarCyMulI4": {"function": {"delta": "12", "convention": "stdcall"}, "ordinal": "304"}, "OLEAUT32.dll:VarMul": {"function": {"delta": "8", "convention": "stdcall"}, "ordinal": "156"}, "OLEAUT32.dll:VarR4FromR8": {"function": {"delta": "8", "convention": "stdcall"}, "ordinal": "71"}, "OLEAUT32.dll:VarR8FromStr": {"function": {"delta": "12", "convention": "stdcall"}, "ordinal": "84"}, "OLEAUT32.dll:VarCyFromR4": {"function": {"delta": "4", "convention": "stdcall"}, "ordinal": "101"}, "OLEAUT32.dll:SafeArrayAllocDescriptor": {"function": {"delta": "4", "convention": "stdcall"}, "ordinal": "36"}, "OLEAUT32.dll:VarCyFromR8": {"function": {"delta": "8", "convention": "stdcall"}, "ordinal": "102"}, "OLEAUT32.dll:VarDecSub": {"function": {"delta": "8", "convention": "stdcall"}, "ordinal": "181"}, "OLEAUT32.dll:GetErrorInfo": {"function": {"delta": "4", "convention": "stdcall"}, "ordinal": "200"}, "OLEAUT32.dll:LPSAFEARRAY_UserUnmarshal": {"function": {"delta": "8", "convention": "stdcall"}, "ordinal": "293"}, "OLEAUT32.dll:VarI8FromStr": {"function": {"delta": "12", "convention": "stdcall"}, "ordinal": "339"}, "OLEAUT32.dll:SafeArrayCreateVector": {"function": {"delta": "8", "convention": "stdcall"}, "ordinal": "411"}, "OLEAUT32.dll:VarUI8FromI1": {"function": {"delta": "4", "convention": "stdcall"}, "ordinal": "438"}, "OLEAUT32.dll:VarDateFromI4": {"function": {"delta": "4", "convention": "stdcall"}, "ordinal": "90"}, "OLEAUT32.dll:VarDateFromI1": {"function": {"delta": "4", "convention": "stdcall"}, "ordinal": "221"}, "OLEAUT32.dll:VarDateFromI2": {"function": {"delta": "4", "convention": "stdcall"}, "ordinal": "89"}, "OLEAUT32.dll:VarBoolFromStr": {"function": {"delta": "12", "convention": "stdcall"}, "ordinal": "125"}, "OLEAUT32.dll:SafeArrayGetIID": {"function": {"delta": "4", "convention": "stdcall"}, "ordinal": "67"}, "OLEAUT32.dll:SysStringByteLen": {"function": {"delta": "0", "convention": "stdcall"}, "ordinal": "149"}, "OLEAUT32.dll:SysAllocStringByteLen": {"function": {"delta": "4", "convention": "stdcall"}, "ordinal": "150"}, "OLEAUT32.dll:VarI4FromCy": {"function": {"delta": "8", "convention": "stdcall"}, "ordinal": "62"}, "OLEAUT32.dll:VariantCopyInd": {"function": {"delta": "4", "convention": "stdcall"}, "ordinal": "11"}, "OLEAUT32.dll:SafeArrayCreate": {"function": {"delta": "8", "convention": "stdcall"}, "ordinal": "15"}, "OLEAUT32.dll:BSTR_UserFree": {"function": {"delta": "4", "convention": "stdcall"}, "ordinal": "286"}, "OLEAUT32.dll:VarCyFromDate": {"function": {"delta": "8", "convention": "stdcall"}, "ordinal": "103"}, "OLEAUT32.dll:VarDecCmpR8": {"function": {"delta": "8", "convention": "stdcall"}, "ordinal": "298"}, "OLEAUT32.dll:VariantCopy": {"function": {"delta": "4", "convention": "stdcall"}, "ordinal": "10"}, "OLEAUT32.dll:VarR8FromCy": {"function": {"delta": "8", "convention": "stdcall"}, "ordinal": "82"}, "OLEAUT32.dll:VarI8FromR8": {"function": {"delta": "8", "convention": "stdcall"}, "ordinal": "336"}, "OLEAUT32.dll:VarUI4FromR8": {"function": {"delta": "8", "convention": "stdcall"}, "ordinal": "274"}, "OLEAUT32.dll:VarCat": {"function": {"delta": "8", "convention": "stdcall"}, "ordinal": "318"}, "OLEAUT32.dll:VarUI4FromR4": {"function": {"delta": "4", "convention": "stdcall"}, "ordinal": "273"}, "OLEAUT32.dll:VarI8FromR4": {"function": {"delta": "4", "convention": "stdcall"}, "ordinal": "335"}, "OLEAUT32.dll:VarR4FromI1": {"function": {"delta": "4", "convention": "stdcall"}, "ordinal": "213"}, "OLEAUT32.dll:VarR4FromI2": {"function": {"delta": "4", "convention": "stdcall"}, "ordinal": "69"}, "OLEAUT32.dll:VarI2FromCy": {"function": {"delta": "8", "convention": "stdcall"}, "ordinal": "52"}, "OLEAUT32.dll:VarR4FromI4": {"function": {"delta": "4", "convention": "stdcall"}, "ordinal": "70"}, "OLEAUT32.dll:VarR4FromI8": {"function": {"delta": "8", "convention": "stdcall"}, "ordinal": "360"}, "OLEAUT32.dll:VarBoolFromDec": {"function": {"delta": "4", "convention": "stdcall"}, "ordinal": "236"}, "OLEAUT32.dll:VarCyFromStr": {"function": {"delta": "12", "convention": "stdcall"}, "ordinal": "104"}, "OLEAUT32.dll:VarBstrFromCy": {"function": {"delta": "16", "convention": "stdcall"}, "ordinal": "113"}, "OLEAUT32.dll:VarUI4FromDec": {"function": {"delta": "4", "convention": "stdcall"}, "ordinal": "282"}, "OLEAUT32.dll:OaEnablePerUserTLibRegistration": {"function": {"delta": "-4", "convention": "stdcall"}, "ordinal": "444"}, "OLEAUT32.dll:VarI1FromDec": {"function": {"delta": "4", "convention": "stdcall"}, "ordinal": "256"}, "OLEAUT32.dll:OleCreatePictureIndirect": {"function": {"delta": "12", "convention": "stdcall"}, "ordinal": "419"}, "OLEAUT32.dll:VarBstrFromDate": {"function": {"delta": "16", "convention": "stdcall"}, "ordinal": "114"}, "OLEAUT32.dll:VarR4FromDisp": {"function": {"delta": "8", "convention": "stdcall"}, "ordinal": "75"}, "OLEAUT32.dll:VarUI2FromDate": {"function": {"delta": "8", "convention": "stdcall"}, "ordinal": "262"}, "OLEAUT32.dll:VarI2FromDate": {"function": {"delta": "8", "convention": "stdcall"}, "ordinal": "53"}, "OLEAUT32.dll:VarUdateFromDate": {"function": {"delta": "12", "convention": "stdcall"}, "ordinal": "331"}, "OLEAUT32.dll:VarDecInt": {"function": {"delta": "4", "convention": "stdcall"}, "ordinal": "188"}, "OLEAUT32.dll:QueryPathOfRegTypeLib": {"function": {"delta": "16", "convention": "stdcall"}, "ordinal": "164"}, "OLEAUT32.dll:OleLoadPictureFile": {"function": {"delta": "16", "convention": "stdcall"}, "ordinal": "422"}, "OLEAUT32.dll:OACleanup": {"function": {"delta": "-4", "convention": "stdcall"}, "ordinal": "500"}, "OLEAUT32.dll:VarUI8FromStr": {"function": {"delta": "12", "convention": "stdcall"}, "ordinal": "435"}, "OLEAUT32.dll:VarUI8FromCy": {"function": {"delta": "8", "convention": "stdcall"}, "ordinal": "433"}, "OLEAUT32.dll:SystemTimeToVariantTime": {"function": {"delta": "4", "convention": "stdcall"}, "ordinal": "184"}, "OLEAUT32.dll:VarCyFromDec": {"function": {"delta": "4", "convention": "stdcall"}, "ordinal": "228"}, "OLEAUT32.dll:SafeArrayGetUBound": {"function": {"delta": "8", "convention": "stdcall"}, "ordinal": "19"}, "OLEAUT32.dll:VarBoolFromCy": {"function": {"delta": "8", "convention": "stdcall"}, "ordinal": "124"}, "OLEAUT32.dll:VarAbs": {"function": {"delta": "4", "convention": "stdcall"}, "ordinal": "168"}, "OLEAUT32.dll:VarBstrFromR8": {"function": {"delta": "16", "convention": "stdcall"}, "ordinal": "112"}, "OLEAUT32.dll:SafeArrayGetLBound": {"function": {"delta": "8", "convention": "stdcall"}, "ordinal": "20"}, "OLEAUT32.dll:BSTR_UserSize": {"function": {"delta": "8", "convention": "stdcall"}, "ordinal": "283"}, "OLEAUT32.dll:VarBstrFromR4": {"function": {"delta": "12", "convention": "stdcall"}, "ordinal": "111"}}}}